COPYING
LICENSE
MANIFEST.in
README.md
setup.py
paks/client.py
paks/defaults.py
paks/env.py
paks/logger.py
paks/plugins.py
paks/schemas.py
paks/settings.py
paks/settings.yml
paks/templates.py
paks/version.py
paks.egg-info/PKG-INFO
paks.egg-info/SOURCES.txt
paks.egg-info/dependency_links.txt
paks.egg-info/entry_points.txt
paks.egg-info/not-zip-safe
paks.egg-info/requires.txt
paks.egg-info/top_level.txt
paks/backends/__init__.py
paks/backends/base.py
paks/backends/docker.py
paks/backends/podman.py
paks/cli/__init__.py
paks/cli/config.py
paks/cli/env.py
paks/cli/run.py
paks/commands/__init__.py
paks/commands/command.py
paks/commands/cp.py
paks/commands/env.py
paks/commands/history.py
paks/commands/inspect.py
paks/commands/state.py
paks/utils/__init__.py
paks/utils/fileio.py
paks/utils/names.py
paks/utils/terminal.py