Metadata-Version: 2.1
Name: paks
Version: 0.1.11
Summary: Interactive container commands.
Home-page: https://github.com/syspack/paks
Author: Vanessa Sochat, Alec Scott
Author-email: vsoch@noreply.github.users.com
Maintainer: Vanessa Sochat, Alec Scott
License: LICENSE
Keywords: containers,interactive commands.
Platform: UNKNOWN
Classifier: Intended Audience :: Science/Research
Classifier: Intended Audience :: Developers
Classifier: License :: OSI Approved :: Apache Software License
Classifier: Programming Language :: Python
Classifier: Topic :: Software Development
Classifier: Topic :: Scientific/Engineering
Classifier: Operating System :: Unix
Classifier: Programming Language :: Python :: 3.8
Provides-Extra: all
